cboe_extractor/__init__.py
cboe_extractor/_cboe_extractor.py
cboe_extractor-0.2.0.dist-info/WHEEL
cboe_extractor-0.2.0.dist-info/METADATA
cboe_extractor-0.2.0.dist-info/RECORD
