Metadata-Version: 2.1
Name: cboe-extractor
Version: 0.2.0
Summary: 
Author: Ernesto Martinez del Pino
Author-email: ernestomar1997@hotmail.com
Requires-Python: >=3.9,<4.0
Classifier: Programming Language :: Python :: 3
Classifier: Programming Language :: Python :: 3.10
Classifier: Programming Language :: Python :: 3.9
Requires-Dist: pandas (>=1.4.4,<2.0.0)
Requires-Dist: python-decouple (>=3.6,<4.0)
Requires-Dist: requests (>=2.28.1,<3.0.0)
